lpgit/__init__.py
lpgit/git_utils.py
lpgit-2.2.9.dist-info/LICENSE
lpgit-2.2.9.dist-info/METADATA
lpgit-2.2.9.dist-info/WHEEL
lpgit-2.2.9.dist-info/top_level.txt
lpgit-2.2.9.dist-info/RECORD
