Metadata-Version: 2.1
Name: lpgit
Version: 2.2.9
Summary: A package for LogicPlum projects
Home-page: https://github.com/jithinj-lp/lpgit.git
Author: LogicPlum
Author-email: jithinj-lp@logicplum.com
License: UNKNOWN
Platform: UNKNOWN
Classifier: Programming Language :: Python :: 3
Classifier: License :: OSI Approved :: MIT License
Classifier: Operating System :: OS Independent
Requires-Python: >=3.6
License-File: LICENSE
Requires-Dist: pygithub
